hybo/__init__.py
hybo-0.0.1.dist-info/LICENSE
hybo-0.0.1.dist-info/METADATA
hybo-0.0.1.dist-info/WHEEL
hybo-0.0.1.dist-info/top_level.txt
hybo-0.0.1.dist-info/RECORD
