Metadata-Version: 2.1
Name: hybo
Version: 0.0.1
Summary: Pure Python Module for Hybo Lidar
Home-page: https://github.com/bluedisk/hybo
Author: Matthew, Lee
Author-email: bluedisk@gmail.com
License: UNKNOWN
Project-URL: Github, https://github.com/bluedisk/hybo
Keywords: 'hybo iLidar pyserial'
Platform: UNKNOWN
Classifier: Programming Language :: Python :: 3
Classifier: License :: OSI Approved :: Apache Software License
Classifier: Operating System :: OS Independent
Requires-Python: >=3.6
License-File: LICENSE
